Workbook

Sheet Read me
A1: LeafLine Tea new branch: practice workbook for the Day 5 lecture
A2: Synthetic case made for the DATA 300 China classroom. Amounts are in currency units.
A4: Sheets
A5: Model: the base (deterministic) year-1 profit model. Blue cells are inputs; orange cells are key outputs.
A6: Model, rows 16-24: a frame for a two-way Data Table (you create the table yourself, steps below).
A7: Simulation: 1,000 Monte Carlo trials with RAND() and NORM.INV(), and a risk summary.
A9: Exercise 1: two-way Data Table (profit by demand and price)
A10: 1. On the Model sheet, select B17:G24 (the corner formula, the prices across and the demands down).
A11: 2. Data > What-If Analysis > Data Table.
A12: 3. Row input cell: B5 (price). Column input cell: B4 (demand). Click OK.
A13: 4. Select C18:G24 and add Home > Conditional Formatting > Color Scales.
A14: Note: the input cells must be on the same sheet as the Data Table.
... A24: 4. To freeze one set of results: copy A1:E1001, then Paste Special > Values on a new sheet.

Sheet Model
A1: LeafLine Tea: new branch, year-1 profit model
A3: Inputs (blue cells: change these) | D3: Outputs
A4: Expected cups sold per year (demand) | B4: 60000 | D4: Cups sold (demand, limited by capacity) | E4: =MIN(B4,B8)
A5: Price per cup | B5: 18 | D5: Revenue | E5: =E4*B5
A6: Variable cost per cup | B6: 7.5 | D6: Variable costs | E6: =E4*B6
A7: Fixed costs per year | B7: 500000 | D7: Profit | E7: =E5-E6-B7
A8: Capacity (most cups the branch can make per year) | B8: 75000 | D8: Break-even demand (cups) | E8: =B7/(B5-B6)
A10: Uncertainty (used by the Simulation sheet)
A11: Demand: standard deviation (normal distribution) | B11: 12000
A12: Variable cost per cup: lowest (uniform distribution) | B12: 6
A13: Variable cost per cup: highest (uniform distribution) | B13: 9
A16: Two-way Data Table: profit by demand (down) and price per cup (across)
A17: Demand \ price | B17: =E7 | C17: 14 | D17: 16 | E17: 18 | F17: 20 | G17: 22
B18: 30000
B19: 40000
B20: 50000
B21: 60000
B22: 70000
B23: 80000
B24: 90000

Sheet Simulation
A1: Trial | B1: Demand | C1: Variable cost per cup | D1: Cups sold | E1: Profit | G1: Risk summary
A2: 1 | B2: =MAX(0,_xlfn.NORM.INV(RAND(),Model!$B$4,Model!$B$11)) | C2: =Model!$B$12+(Model!$B$13-Model!$B$12)*RAND() | D2: =MIN(B2,Model!$B$8) | E2: =D2*(Model!$B$5-C2)-Model!$B$7 | G2: Trials | H2: =COUNT(E2:E1001)
A3: 2 | B3: =MAX(0,_xlfn.NORM.INV(RAND(),Model!$B$4,Model!$B$11)) | C3: =Model!$B$12+(Model!$B$13-Model!$B$12)*RAND() | D3: =MIN(B3,Model!$B$8) | E3: =D3*(Model!$B$5-C3)-Model!$B$7 | G3: Average profit | H3: =AVERAGE(E2:E1001)
A4: 3 | B4: =MAX(0,_xlfn.NORM.INV(RAND(),Model!$B$4,Model!$B$11)) | C4: =Model!$B$12+(Model!$B$13-Model!$B$12)*RAND() | D4: =MIN(B4,Model!$B$8) | E4: =D4*(Model!$B$5-C4)-Model!$B$7 | G4: Standard deviation | H4: =_xlfn.STDEV.S(E2:E1001)
A5: 4 | B5: =MAX(0,_xlfn.NORM.INV(RAND(),Model!$B$4,Model!$B$11)) | C5: =Model!$B$12+(Model!$B$13-Model!$B$12)*RAND() | D5: =MIN(B5,Model!$B$8) | E5: =D5*(Model!$B$5-C5)-Model!$B$7 | G5: Minimum (worst trial) | H5: =MIN(E2:E1001)
A6: 5 | B6: =MAX(0,_xlfn.NORM.INV(RAND(),Model!$B$4,Model!$B$11)) | C6: =Model!$B$12+(Model!$B$13-Model!$B$12)*RAND() | D6: =MIN(B6,Model!$B$8) | E6: =D6*(Model!$B$5-C6)-Model!$B$7 | G6: Maximum (best trial) | H6: =MAX(E2:E1001)
A7: 6 | B7: =MAX(0,_xlfn.NORM.INV(RAND(),Model!$B$4,Model!$B$11)) | C7: =Model!$B$12+(Model!$B$13-Model!$B$12)*RAND() | D7: =MIN(B7,Model!$B$8) | E7: =D7*(Model!$B$5-C7)-Model!$B$7 | G7: Probability of a loss | H7: =COUNTIF(E2:E1001,"<0")/H2
A8: 7 | B8: =MAX(0,_xlfn.NORM.INV(RAND(),Model!$B$4,Model!$B$11)) | C8: =Model!$B$12+(Model!$B$13-Model!$B$12)*RAND() | D8: =MIN(B8,Model!$B$8) | E8: =D8*(Model!$B$5-C8)-Model!$B$7 | G8: 5th percentile (P5) | H8: =_xlfn.PERCENTILE.INC(E2:E1001,0.05)
A9: 8 | B9: =MAX(0,_xlfn.NORM.INV(RAND(),Model!$B$4,Model!$B$11)) | C9: =Model!$B$12+(Model!$B$13-Model!$B$12)*RAND() | D9: =MIN(B9,Model!$B$8) | E9: =D9*(Model!$B$5-C9)-Model!$B$7 | G9: 95th percentile (P95) | H9: =_xlfn.PERCENTILE.INC(E2:E1001,0.95)
A10: 9 | B10: =MAX(0,_xlfn.NORM.INV(RAND(),Model!$B$4,Model!$B$11)) | C10: =Model!$B$12+(Model!$B$13-Model!$B$12)*RAND() | D10: =MIN(B10,Model!$B$8) | E10: =D10*(Model!$B$5-C10)-Model!$B$7 | G10: Average of the worst 5% of trials | H10: =AVERAGEIF(E2:E1001,"<="&H8)
A11: 10 | B11: =MAX(0,_xlfn.NORM.INV(RAND(),Model!$B$4,Model!$B$11)) | C11: =Model!$B$12+(Model!$B$13-Model!$B$12)*RAND() | D11: =MIN(B11,Model!$B$8) | E11: =D11*(Model!$B$5-C11)-Model!$B$7 | G11: Profit at average inputs (Model!E7) | H11: =Model!E7
A12: 11 | B12: =MAX(0,_xlfn.NORM.INV(RAND(),Model!$B$4,Model!$B$11)) | C12: =Model!$B$12+(Model!$B$13-Model!$B$12)*RAND() | D12: =MIN(B12,Model!$B$8) | E12: =D12*(Model!$B$5-C12)-Model!$B$7
A13: 12 | B13: =MAX(0,_xlfn.NORM.INV(RAND(),Model!$B$4,Model!$B$11)) | C13: =Model!$B$12+(Model!$B$13-Model!$B$12)*RAND() | D13: =MIN(B13,Model!$B$8) | E13: =D13*(Model!$B$5-C13)-Model!$B$7
A14: 13 | B14: =MAX(0,_xlfn.NORM.INV(RAND(),Model!$B$4,Model!$B$11)) | C14: =Model!$B$12+(Model!$B$13-Model!$B$12)*RAND() | D14: =MIN(B14,Model!$B$8) | E14: =D14*(Model!$B$5-C14)-Model!$B$7
A15: 14 | B15: =MAX(0,_xlfn.NORM.INV(RAND(),Model!$B$4,Model!$B$11)) | C15: =Model!$B$12+(Model!$B$13-Model!$B$12)*RAND() | D15: =MIN(B15,Model!$B$8) | E15: =D15*(Model!$B$5-C15)-Model!$B$7
A16: 15 | B16: =MAX(0,_xlfn.NORM.INV(RAND(),Model!$B$4,Model!$B$11)) | C16: =Model!$B$12+(Model!$B$13-Model!$B$12)*RAND() | D16: =MIN(B16,Model!$B$8) | E16: =D16*(Model!$B$5-C16)-Model!$B$7
A17: 16 | B17: =MAX(0,_xlfn.NORM.INV(RAND(),Model!$B$4,Model!$B$11)) | C17: =Model!$B$12+(Model!$B$13-Model!$B$12)*RAND() | D17: =MIN(B17,Model!$B$8) | E17: =D17*(Model!$B$5-C17)-Model!$B$7
A18: 17 | B18: =MAX(0,_xlfn.NORM.INV(RAND(),Model!$B$4,Model!$B$11)) | C18: =Model!$B$12+(Model!$B$13-Model!$B$12)*RAND() | D18: =MIN(B18,Model!$B$8) | E18: =D18*(Model!$B$5-C18)-Model!$B$7
A19: 18 | B19: =MAX(0,_xlfn.NORM.INV(RAND(),Model!$B$4,Model!$B$11)) | C19: =Model!$B$12+(Model!$B$13-Model!$B$12)*RAND() | D19: =MIN(B19,Model!$B$8) | E19: =D19*(Model!$B$5-C19)-Model!$B$7
A20: 19 | B20: =MAX(0,_xlfn.NORM.INV(RAND(),Model!$B$4,Model!$B$11)) | C20: =Model!$B$12+(Model!$B$13-Model!$B$12)*RAND() | D20: =MIN(B20,Model!$B$8) | E20: =D20*(Model!$B$5-C20)-Model!$B$7
A21: 20 | B21: =MAX(0,_xlfn.NORM.INV(RAND(),Model!$B$4,Model!$B$11)) | C21: =Model!$B$12+(Model!$B$13-Model!$B$12)*RAND() | D21: =MIN(B21,Model!$B$8) | E21: =D21*(Model!$B$5-C21)-Model!$B$7
A22: 21 | B22: =MAX(0,_xlfn.NORM.INV(RAND(),Model!$B$4,Model!$B$11)) | C22: =Model!$B$12+(Model!$B$13-Model!$B$12)*RAND() | D22: =MIN(B22,Model!$B$8) | E22: =D22*(Model!$B$5-C22)-Model!$B$7
A23: 22 | B23: =MAX(0,_xlfn.NORM.INV(RAND(),Model!$B$4,Model!$B$11)) | C23: =Model!$B$12+(Model!$B$13-Model!$B$12)*RAND() | D23: =MIN(B23,Model!$B$8) | E23: =D23*(Model!$B$5-C23)-Model!$B$7
... A1001: 1000 | B1001: =MAX(0,_xlfn.NORM.INV(RAND(),Model!$B$4,Model!$B$11)) | C1001: =Model!$B$12+(Model!$B$13-Model!$B$12)*RAND() | D1001: =MIN(B1001,Model!$B$8) | E1001: =D1001*(Model!$B$5-C1001)-Model!$B$7
